aeropy/__init__.py
aeropy/aerodynamics/__init__.py
aeropy/aircraft/__init__.py
aeropy/aircraft/corrections.py
aeropy/aircraft/geometry.py
aeropy/aircraft/noise.py
aeropy/airfoils/__init__.py
aeropy/airfoils/analysis.py
aeropy/airfoils/shapes.py
aeropy/airfoils/executables/__init__.py
aeropy/airfoils/executables/__init__.pyc
aeropy/airfoils/executables/api.py
aeropy/airfoils/executables/api.pyc
aeropy/airfoils/executables/libiomp5md.dll
aeropy/airfoils/executables/su2edu.exe
aeropy/airfoils/executables/xfoil.exe
aeropy/airfoils/executables/__pycache__/__init__.cpython-37.pyc
aeropy/airfoils/executables/__pycache__/api.cpython-37.pyc
aeropy/airfoils/executables/su2edu/ConfigFile_INV.cfg
aeropy/airfoils/executables/su2edu/ConfigFile_RANS.cfg
aeropy/airfoils/executables/su2edu/mesh_NACA0012_1E-4m.su2
aeropy/airfoils/executables/su2edu/mesh_NACA0012_1E-5m.su2
aeropy/airfoils/executables/su2edu/mesh_NACA0012_1E-6m.su2
aeropy/airfoils/executables/su2edu/mesh_NACA0012_1E-7m.su2
aeropy/airfoils/executables/su2edu/mesh_NACA0012_INV.su2
aeropy/airfoils/external/__init__.py
aeropy/airfoils/external/naca.py
aeropy/airlines/__init__.py
aeropy/airlines/analysis.py
aeropy/airlines/databases/F41SCHEDULE_P52_18082017/L_AIRCRAFT_CONFIG.csv_
aeropy/airlines/databases/F41SCHEDULE_P52_18082017/L_AIRCRAFT_GROUP.csv_
aeropy/airlines/databases/F41SCHEDULE_P52_18082017/L_AIRCRAFT_TYPE.csv_
aeropy/airlines/databases/F41SCHEDULE_P52_18082017/L_AIRLINE_ID.csv_
aeropy/airlines/databases/F41SCHEDULE_P52_18082017/L_CARRIER_GROUP.csv_
aeropy/airlines/databases/F41SCHEDULE_P52_18082017/L_CARRIER_GROUP_NEW.csv_
aeropy/airlines/databases/F41SCHEDULE_P52_18082017/L_CARRIER_HISTORY.csv_
aeropy/airlines/databases/F41SCHEDULE_P52_18082017/L_COSTS.csv_
aeropy/airlines/databases/F41SCHEDULE_P52_18082017/L_QUARTERS.csv_
aeropy/airlines/databases/F41SCHEDULE_P52_18082017/L_REGION.csv_
aeropy/airlines/databases/F41SCHEDULE_P52_18082017/L_UNIQUE_CARRIERS.csv_
aeropy-0.2.dist-info/LICENSE.md
aeropy-0.2.dist-info/METADATA
aeropy-0.2.dist-info/WHEEL
aeropy-0.2.dist-info/top_level.txt
aeropy-0.2.dist-info/RECORD
