Metadata-Version: 2.1
Name: aeropy
Version: 0.2
Summary: A universal aerospace engineering toolbox
Home-page: https://bitbucket.org/lukas-mueller/aeropy
Author: Lukas Mueller
Author-email: lukas.mueller94@gmail.com
License: MIT License
Download-URL: https://bitbucket.org/lukas-mueller/aeropy/raw/master/dist/aeropy-0.2.tar.gz
Keywords: aerospace engineering airfoils noise aircraft
Platform: UNKNOWN
Classifier: Development Status :: 4 - Beta
Classifier: License :: OSI Approved :: MIT License
Classifier: Programming Language :: Python :: 3.7
Classifier: Intended Audience :: Science/Research
Classifier: Topic :: Scientific/Engineering
Requires-Python: >=3
Requires-Dist: matplotlib
Requires-Dist: numpy
Requires-Dist: pandas
Requires-Dist: scipy
